common/__init__.py
common/social_media_utils.py
common/templating_utils.py
post-to-bluesky/__init__.py
post-to-bluesky/post_to_bluesky.py
post-to-facebook/__init__.py
post-to-facebook/post_to_facebook.py
post-to-instagram/__init__.py
post-to-instagram/post_to_instagram.py
post-to-linkedin/__init__.py
post-to-linkedin/post_to_linkedin.py
post-to-threads/__init__.py
post-to-threads/post_to_threads.py
post-to-x/__init__.py
post-to-x/post_to_x.py
post-to-youtube/__init__.py
post-to-youtube/post_to_youtube.py
post-to-youtube/update_youtube.py
social_cli/GUIDE.md
social_cli/__init__.py
social_cli/cli.py
social_media_posters-1.18.0.dist-info/licenses/LICENSE
social_media_posters-1.18.0.dist-info/METADATA
social_media_posters-1.18.0.dist-info/WHEEL
social_media_posters-1.18.0.dist-info/entry_points.txt
social_media_posters-1.18.0.dist-info/top_level.txt
social_media_posters-1.18.0.dist-info/RECORD
