Metadata-Version: 2.4
Name: social-media-posters
Version: 1.18.0
Summary: CLI and GitHub Actions for posting to various social media platforms
Author: Gerald Nguyen
License: MIT
Project-URL: Homepage, https://github.com/geraldnguyen/social-media-posters
Project-URL: Repository, https://github.com/geraldnguyen/social-media-posters
Project-URL: Issues, https://github.com/geraldnguyen/social-media-posters/issues
Keywords: social-media,automation,cli,github-actions,twitter,facebook,instagram,threads,linkedin,youtube,bluesky
Classifier: Development Status :: 4 - Beta
Classifier: Intended Audience :: Developers
Classifier: License :: OSI Approved :: MIT License
Classifier: Programming Language :: Python :: 3
Classifier: Programming Language :: Python :: 3.8
Classifier: Programming Language :: Python :: 3.9
Classifier: Programming Language :: Python :: 3.10
Classifier: Programming Language :: Python :: 3.11
Classifier: Programming Language :: Python :: 3.12
Classifier: Topic :: Software Development :: Libraries :: Python Modules
Requires-Python: >=3.8
License-File: LICENSE
Requires-Dist: requests>=2.31.0
Requires-Dist: python-dotenv
Requires-Dist: jsonpath-ng
Requires-Dist: click>=8.0.0
Provides-Extra: x
Requires-Dist: tweepy>=4.14.0; extra == "x"
Provides-Extra: facebook
Requires-Dist: facebook-sdk>=3.1.0; extra == "facebook"
Provides-Extra: instagram
Requires-Dist: pillow>=10.0.0; extra == "instagram"
Provides-Extra: threads
Provides-Extra: linkedin
Provides-Extra: bluesky
Requires-Dist: atproto>=0.0.38; extra == "bluesky"
Requires-Dist: beautifulsoup4>=4.12.0; extra == "bluesky"
Requires-Dist: lxml>=4.9.0; extra == "bluesky"
Provides-Extra: youtube
Requires-Dist: google-api-python-client>=2.100.0; extra == "youtube"
Requires-Dist: google-auth>=2.23.0; extra == "youtube"
Requires-Dist: google-auth-oauthlib>=1.1.0; extra == "youtube"
Requires-Dist: google-auth-httplib2>=0.1.1; extra == "youtube"
Provides-Extra: all
Requires-Dist: tweepy>=4.14.0; extra == "all"
Requires-Dist: facebook-sdk>=3.1.0; extra == "all"
Requires-Dist: pillow>=10.0.0; extra == "all"
Requires-Dist: atproto>=0.0.38; extra == "all"
Requires-Dist: beautifulsoup4>=4.12.0; extra == "all"
Requires-Dist: lxml>=4.9.0; extra == "all"
Requires-Dist: google-api-python-client>=2.100.0; extra == "all"
Requires-Dist: google-auth>=2.23.0; extra == "all"
Requires-Dist: google-auth-oauthlib>=1.1.0; extra == "all"
Requires-Dist: google-auth-httplib2>=0.1.1; extra == "all"
Dynamic: license-file
